laima/__init__.py
laima/exceptions.py
laima/core/__init__.py
laima/core/context.py
laima/core/functions.py
laima/core/lifespans.py
laima/core/register.py
laima/utils/__init__.py
laima/utils/empty.py
laima/utils/lock.py
laima/utils/object.py
laima-0.1.0.dist-info/licenses/LICENSE
laima-0.1.0.dist-info/METADATA
laima-0.1.0.dist-info/WHEEL
laima-0.1.0.dist-info/top_level.txt
laima-0.1.0.dist-info/RECORD
