Metadata-Version: 2.4
Name: laima
Version: 0.1.0
Summary: A powerful dependency injection framework that automatically managing objects lifespan, promoting loose coupling, improving testability, and centralizing configuration for easier maintenance.
Author: Mateusz Baran
Maintainer: Mateusz Baran
License: MIT License
Project-URL: repository, https://github.com/mateuszbaransanok/laima
Keywords: Dependency Injection
Classifier: Development Status :: 4 - Beta
Classifier: Programming Language :: Python
Classifier: Programming Language :: Python :: 3
Classifier: Programming Language :: Python :: 3 :: Only
Classifier: Programming Language :: Python :: 3.10
Classifier: Programming Language :: Python :: 3.11
Classifier: Programming Language :: Python :: 3.12
Classifier: Programming Language :: Python :: 3.13
Classifier: Operating System :: OS Independent
Classifier: License :: OSI Approved :: MIT License
Requires-Python: >=3.10
License-File: LICENSE
Dynamic: license-file
